Particle_Board_REPL/PBR-defaults.yaml
Particle_Board_REPL/SPR-defaults.yaml
Particle_Board_REPL/__init__.py
Particle_Board_REPL/__main__.py
Particle_Board_REPL/core.py
Particle_Board_REPL/logs.py
Particle_Board_REPL/main.py
Particle_Board_REPL/options.py
Particle_Board_REPL/particle.py
Particle_Board_REPL/repl.py
Particle_Board_REPL-2.0.7.dist-info/METADATA
Particle_Board_REPL-2.0.7.dist-info/WHEEL
Particle_Board_REPL-2.0.7.dist-info/entry_points.txt
Particle_Board_REPL-2.0.7.dist-info/top_level.txt
Particle_Board_REPL-2.0.7.dist-info/RECORD
