Metadata-Version: 2.1
Name: Particle-Board-REPL
Version: 2.0.7
Summary: An extensible application framework with REPL for creating processes with side effects.
Home-page: https://github.com/EricGebhart/Particle_Board_REPL
Author: Eric Gebhart
Author-email: e.a.gebhart@gmail.com
License: MIT
Platform: UNKNOWN
Requires-Dist: regex
Requires-Dist: pyserial
Requires-Dist: pythondialog
Requires-Dist: pyYAML
